drs_cli/__init__.py
drs_cli/client.py
drs_cli/errors.py
drs_cli/models.py
tests/__init__.py
tests/mock_data.py
tests/test_client.py
tests/test_errors.py
drs_cli-0.2.3.dist-info/LICENCE
drs_cli-0.2.3.dist-info/METADATA
drs_cli-0.2.3.dist-info/WHEEL
drs_cli-0.2.3.dist-info/top_level.txt
drs_cli-0.2.3.dist-info/RECORD
