Metadata-Version: 2.1
Name: drs-cli
Version: 0.2.3
Summary: GA4GH DRS Client
Home-page: https://github.com/elixir-cloud-aai/DRS-cli.git
Author: ELIXIR Cloud & AAI
Author-email: sarthakgupta072@gmail.com
License: Apache License 2.0
Keywords: ga4gh drs elixir rest restful api app server python
Platform: UNKNOWN
Classifier: License :: OSI Approved :: Apache Software License
Classifier: Development Status :: 3 - Alpha
Classifier: Intended Audience :: Science/Research
Classifier: Topic :: Scientific/Engineering :: Bio-Informatics
Classifier: Natural Language :: English
Classifier: Programming Language :: Python :: 3.6
Classifier: Programming Language :: Python :: 3.7
Classifier: Programming Language :: Python :: 3.8
Requires-Python: >=3.6
